README
pollinator
setup.py
pollinator/__init__.py
pollinator/poll.py
pollinator/utils.py
pollinator.egg-info/PKG-INFO
pollinator.egg-info/SOURCES.txt
pollinator.egg-info/dependency_links.txt
pollinator.egg-info/top_level.txt