Metadata-Version: 1.1
Name: pollinator
Version: 0.0.3
Summary: Pollinator is a Python poll and generator based package for writing simple
Home-page: https://github.com/akfullfo/pollinator
Author: Andrew Fullford
Author-email: pypi102014@fullford.com
License: Apache License, Version 2.0
Download-URL: https://github.com/akfullfo/pollinator/tarball/0.0.3
Platform: Linux
Platform: BSD
Platform: Mac OS X
Classifier: Development Status :: 1 - Planning
Classifier: Environment :: Other Environment
Classifier: Intended Audience :: Developers
Classifier: License :: OSI Approved :: Apache Software License
Classifier: Operating System :: POSIX :: Linux
Classifier: Operating System :: POSIX :: BSD
Classifier: Operating System :: MacOS :: MacOS X
Classifier: Programming Language :: Python :: 2.7
Classifier: Topic :: Communications
Classifier: Topic :: Internet
Classifier: Topic :: System :: Distributed Computing
Classifier: Topic :: System :: Networking
Provides: pollinator
